{
  "0": {
    "0": {
      "0": {
        "h": "null_of_0_0_0_h",
        "b": "null_of_0_0_0_b"
      },
      "1": {
        "h": "null_of_0_0_1_h",
        "b": "null_of_0_0_1_b zzz"
      },
      "2": {
        "h": "null_of_0_0_2_h",
        "b": "null_of_0_0_2_b"
      }
    },
    
    "1": {
      "0": {
        "h": "null_of_0_1_0_h",
        "b": "null_of_0_1_0_b"
      },
      "1": {
        "h": "null_of_0_1_1_h",
        "b": "null_of_0_1_1_b"
      },
      "2": {
        "h": "null_of_0_1_2_h",
        "b": "null_of_0_1_2_b"
      }
    },
    "2": {
      "0": {
        "h": "null_of_0_2_0_h",
        "b": "null_of_0_2_0_b"
      },
      "1": {
        "h": "null_of_0_2_1_h",
        "b": "null_of_0_2_1_b"
      },
      "2": {
        "h": "null_of_0_2_2_h",
        "b": "null_of_0_2_2_b"
      }
    },
    "3": {
      "0": {
        "h": "null_of_0_3_0_h",
        "b": "null_of_0_3_0_b"
      },
      "1": {
        "h": "null_of_0_3_1_h",
        "b": "null_of_0_3_1_b"
      },
      "2": {
        "h": "null_of_0_3_2_h",
        "b": "null_of_0_3_2_b"
      }
    },
    "4": {
      "0": {
        "h": "null_of_0_4_0_h",
        "b": "null_of_0_4_0_b"
      },
      "1": {
        "h": "null_of_0_4_1_h",
        "b": "null_of_0_4_1_b"
      },
      "2": {
        "h": "null_of_0_4_2_h",
        "b": "null_of_0_4_2_b"
      }
    },
    "5": {
      "0": {
        "h": "null_of_0_5_0_h",
        "b": "null_of_0_5_0_b"
      },
      "1": {
        "h": "null_of_0_5_1_h",
        "b": "null_of_0_5_1_b"
      },
      "2": {
        "h": "null_of_0_5_2_h",
        "b": "null_of_0_5_2_b"
      }
    },
    "6": {
      "0": {
        "h": "null_of_0_6_0_h",
        "b": "null_of_0_6_0_b"
      },
      "1": {
        "h": "null_of_0_6_1_h",
        "b": "null_of_0_6_1_b"
      },
      "2": {
        "h": "null_of_0_6_2_h",
        "b": "null_of_0_6_2_b"
      }
    },
    "7": {
      "0": {
        "h": "null_of_0_7_0_h",
        "b": "null_of_0_7_0_b"
      },
      "1": {
        "h": "null_of_0_7_1_h",
        "b": "null_of_0_7_1_b"
      },
      "2": {
        "h": "null_of_0_7_2_h",
        "b": "null_of_0_7_2_b"
      }
    },
    "8": {
      "0": {
        "h": "null_of_0_8_0_h",
        "b": "null_of_0_8_0_b"
      },
      "1": {
        "h": "null_of_0_8_1_h",
        "b": "null_of_0_8_1_b"
      },
      "2": {
        "h": "null_of_0_8_2_h",
        "b": "null_of_0_8_2_b"
      }
    },
    "9": {
      "0": {
        "h": "null_of_0_9_0_h",
        "b": "null_of_0_9_0_b"
      },
      "1": {
        "h": "null_of_0_9_1_h",
        "b": "null_of_0_9_1_b"
      },
      "2": {
        "h": "null_of_0_9_2_h",
        "b": "null_of_0_9_2_b"
      }
    },
    "10": {
      "0": {
        "h": "null_of_0_10_0_h",
        "b": "null_of_0_10_0_b"
      },
      "1": {
        "h": "null_of_0_10_1_h",
        "b": "null_of_0_10_1_b"
      },
      "2": {
        "h": "null_of_0_10_2_h",
        "b": "null_of_0_10_2_b"
      }
    },
    "11": {
      "0": {
        "h": "null_of_0_11_0_h",
        "b": "null_of_0_11_0_b"
      },
      "1": {
        "h": "null_of_0_11_1_h",
        "b": "null_of_0_11_1_b"
      },
      "2": {
        "h": "null_of_0_11_2_h",
        "b": "null_of_0_11_2_b"
      }
    },
    "12": {
      "0": {
        "h": "null_of_0_12_0_h",
        "b": "null_of_0_12_0_b"
      },
      "1": {
        "h": "null_of_0_12_1_h",
        "b": "null_of_0_12_1_b"
      },
      "2": {
        "h": "null_of_0_12_2_h",
        "b": "null_of_0_12_2_b"
      }
    },
    "13": {
      "0": {
        "h": "null_of_0_13_0_h",
        "b": "null_of_0_13_0_b"
      },
      "1": {
        "h": "null_of_0_13_1_h",
        "b": "null_of_0_13_1_b"
      },
      "2": {
        "h": "null_of_0_13_2_h",
        "b": "null_of_0_13_2_b"
      }
    },
    "14": {
      "0": {
        "h": "null_of_0_14_0_h",
        "b": "null_of_0_14_0_b"
      },
      "1": {
        "h": "null_of_0_14_1_h",
        "b": "null_of_0_14_1_b"
      },
      "2": {
        "h": "null_of_0_14_2_h",
        "b": "null_of_0_14_2_b"
      }
    },
    "15": {
      "0": {
        "h": "null_of_0_15_0_h",
        "b": "null_of_0_15_0_b"
      },
      "1": {
        "h": "null_of_0_15_1_h",
        "b": "null_of_0_15_1_b"
      },
      "2": {
        "h": "null_of_0_15_2_h",
        "b": "null_of_0_15_2_b"
      }
    },
    "16": {
      "0": {
        "h": "null_of_0_16_0_h",
        "b": "null_of_0_16_0_b"
      },
      "1": {
        "h": "null_of_0_16_1_h",
        "b": "null_of_0_16_1_b"
      },
      "2": {
        "h": "null_of_0_16_2_h",
        "b": "null_of_0_16_2_b"
      }
    },
    "17": {
      "0": {
        "h": "null_of_0_17_0_h",
        "b": "null_of_0_17_0_b"
      },
      "1": {
        "h": "null_of_0_17_1_h",
        "b": "null_of_0_17_1_b"
      },
      "2": {
        "h": "null_of_0_17_2_h",
        "b": "null_of_0_17_2_b"
      }
    },
    "18": {
      "0": {
        "h": "null_of_0_18_0_h",
        "b": "null_of_0_18_0_b"
      },
      "1": {
        "h": "null_of_0_18_1_h",
        "b": "null_of_0_18_1_b"
      },
      "2": {
        "h": "null_of_0_18_2_h",
        "b": "null_of_0_18_2_b"
      }
    },
    "19": {
      "0": {
        "h": "null_of_0_19_0_h",
        "b": "null_of_0_19_0_b"
      },
      "1": {
        "h": "null_of_0_19_1_h",
        "b": "null_of_0_19_1_b"
      },
      "2": {
        "h": "null_of_0_19_2_h",
        "b": "null_of_0_19_2_b"
      }
    }
  },
  "1": {
    "0": {
      "0": {
        "h": "null_of_1_0_0_h",
        "b": "null_of_1_0_0_b"
      },
      "1": {
        "h": "null_of_1_0_1_h",
        "b": "null_of_1_0_1_b"
      },
      "2": {
        "h": "null_of_1_0_2_h",
        "b": "null_of_1_0_2_b"
      }
    },
    "1": {
      "0": {
        "h": "null_of_1_1_0_h",
        "b": "null_of_1_1_0_b"
      },
      "1": {
        "h": "null_of_1_1_1_h",
        "b": "null_of_1_1_1_b"
      },
      "2": {
        "h": "null_of_1_1_2_h",
        "b": "null_of_1_1_2_b"
      }
    },
    "2": {
      "0": {
        "h": "null_of_1_2_0_h",
        "b": "null_of_1_2_0_b"
      },
      "1": {
        "h": "null_of_1_2_1_h",
        "b": "null_of_1_2_1_b"
      },
      "2": {
        "h": "null_of_1_2_2_h",
        "b": "null_of_1_2_2_b"
      }
    },
    "3": {
      "0": {
        "h": "null_of_1_3_0_h",
        "b": "null_of_1_3_0_b"
      },
      "1": {
        "h": "null_of_1_3_1_h",
        "b": "null_of_1_3_1_b"
      },
      "2": {
        "h": "null_of_1_3_2_h",
        "b": "null_of_1_3_2_b"
      }
    },
    "4": {
      "0": {
        "h": "null_of_1_4_0_h",
        "b": "null_of_1_4_0_b"
      },
      "1": {
        "h": "null_of_1_4_1_h",
        "b": "null_of_1_4_1_b"
      },
      "2": {
        "h": "null_of_1_4_2_h",
        "b": "null_of_1_4_2_b"
      }
    },
    "5": {
      "0": {
        "h": "null_of_1_5_0_h",
        "b": "null_of_1_5_0_b"
      },
      "1": {
        "h": "null_of_1_5_1_h",
        "b": "null_of_1_5_1_b"
      },
      "2": {
        "h": "null_of_1_5_2_h",
        "b": "null_of_1_5_2_b"
      }
    },
    "6": {
      "0": {
        "h": "null_of_1_6_0_h",
        "b": "null_of_1_6_0_b"
      },
      "1": {
        "h": "null_of_1_6_1_h",
        "b": "null_of_1_6_1_b"
      },
      "2": {
        "h": "null_of_1_6_2_h",
        "b": "null_of_1_6_2_b"
      }
    },
    "7": {
      "0": {
        "h": "null_of_1_7_0_h",
        "b": "null_of_1_7_0_b"
      },
      "1": {
        "h": "null_of_1_7_1_h",
        "b": "null_of_1_7_1_b"
      },
      "2": {
        "h": "null_of_1_7_2_h",
        "b": "null_of_1_7_2_b"
      }
    },
    "8": {
      "0": {
        "h": "null_of_1_8_0_h",
        "b": "null_of_1_8_0_b"
      },
      "1": {
        "h": "null_of_1_8_1_h",
        "b": "null_of_1_8_1_b"
      },
      "2": {
        "h": "null_of_1_8_2_h",
        "b": "null_of_1_8_2_b"
      }
    },
    "9": {
      "0": {
        "h": "null_of_1_9_0_h",
        "b": "null_of_1_9_0_b"
      },
      "1": {
        "h": "null_of_1_9_1_h",
        "b": "null_of_1_9_1_b"
      },
      "2": {
        "h": "null_of_1_9_2_h",
        "b": "null_of_1_9_2_b"
      }
    },
    "10": {
      "0": {
        "h": "null_of_1_10_0_h",
        "b": "null_of_1_10_0_b"
      },
      "1": {
        "h": "null_of_1_10_1_h",
        "b": "null_of_1_10_1_b"
      },
      "2": {
        "h": "null_of_1_10_2_h",
        "b": "null_of_1_10_2_b"
      }
    },
    "11": {
      "0": {
        "h": "null_of_1_11_0_h",
        "b": "null_of_1_11_0_b"
      },
      "1": {
        "h": "null_of_1_11_1_h",
        "b": "null_of_1_11_1_b"
      },
      "2": {
        "h": "null_of_1_11_2_h",
        "b": "null_of_1_11_2_b"
      }
    },
    "12": {
      "0": {
        "h": "null_of_1_12_0_h",
        "b": "null_of_1_12_0_b"
      },
      "1": {
        "h": "null_of_1_12_1_h",
        "b": "null_of_1_12_1_b"
      },
      "2": {
        "h": "null_of_1_12_2_h",
        "b": "null_of_1_12_2_b"
      }
    },
    "13": {
      "0": {
        "h": "null_of_1_13_0_h",
        "b": "null_of_1_13_0_b"
      },
      "1": {
        "h": "null_of_1_13_1_h",
        "b": "null_of_1_13_1_b"
      },
      "2": {
        "h": "null_of_1_13_2_h",
        "b": "null_of_1_13_2_b"
      }
    },
    "14": {
      "0": {
        "h": "null_of_1_14_0_h",
        "b": "null_of_1_14_0_b"
      },
      "1": {
        "h": "null_of_1_14_1_h",
        "b": "null_of_1_14_1_b"
      },
      "2": {
        "h": "null_of_1_14_2_h",
        "b": "null_of_1_14_2_b"
      }
    },
    "15": {
      "0": {
        "h": "null_of_1_15_0_h",
        "b": "null_of_1_15_0_b"
      },
      "1": {
        "h": "null_of_1_15_1_h",
        "b": "null_of_1_15_1_b"
      },
      "2": {
        "h": "null_of_1_15_2_h",
        "b": "null_of_1_15_2_b"
      }
    },
    "16": {
      "0": {
        "h": "null_of_1_16_0_h",
        "b": "null_of_1_16_0_b"
      },
      "1": {
        "h": "null_of_1_16_1_h",
        "b": "null_of_1_16_1_b"
      },
      "2": {
        "h": "null_of_1_16_2_h",
        "b": "null_of_1_16_2_b"
      }
    },
    "17": {
      "0": {
        "h": "null_of_1_17_0_h",
        "b": "null_of_1_17_0_b"
      },
      "1": {
        "h": "null_of_1_17_1_h",
        "b": "null_of_1_17_1_b"
      },
      "2": {
        "h": "null_of_1_17_2_h",
        "b": "null_of_1_17_2_b"
      }
    },
    "18": {
      "0": {
        "h": "null_of_1_18_0_h",
        "b": "null_of_1_18_0_b"
      },
      "1": {
        "h": "null_of_1_18_1_h",
        "b": "null_of_1_18_1_b"
      },
      "2": {
        "h": "null_of_1_18_2_h",
        "b": "null_of_1_18_2_b"
      }
    },
    "19": {
      "0": {
        "h": "null_of_1_19_0_h",
        "b": "null_of_1_19_0_b"
      },
      "1": {
        "h": "null_of_1_19_1_h",
        "b": "null_of_1_19_1_b"
      },
      "2": {
        "h": "null_of_1_19_2_h",
        "b": "null_of_1_19_2_b"
      }
    }
  },
  "2": {
    "0": {
      "0": {
        "h": "null_of_2_0_0_h",
        "b": "null_of_2_0_0_b"
      },
      "1": {
        "h": "null_of_2_0_1_h",
        "b": "null_of_2_0_1_b"
      },
      "2": {
        "h": "null_of_2_0_2_h",
        "b": "null_of_2_0_2_b"
      }
    },
    "1": {
      "0": {
        "h": "null_of_2_1_0_h",
        "b": "null_of_2_1_0_b"
      },
      "1": {
        "h": "null_of_2_1_1_h",
        "b": "null_of_2_1_1_b"
      },
      "2": {
        "h": "null_of_2_1_2_h",
        "b": "null_of_2_1_2_b"
      }
    },
    "2": {
      "0": {
        "h": "null_of_2_2_0_h",
        "b": "null_of_2_2_0_b"
      },
      "1": {
        "h": "null_of_2_2_1_h",
        "b": "null_of_2_2_1_b"
      },
      "2": {
        "h": "null_of_2_2_2_h",
        "b": "null_of_2_2_2_b"
      }
    },
    "3": {
      "0": {
        "h": "null_of_2_3_0_h",
        "b": "null_of_2_3_0_b"
      },
      "1": {
        "h": "null_of_2_3_1_h",
        "b": "null_of_2_3_1_b"
      },
      "2": {
        "h": "null_of_2_3_2_h",
        "b": "null_of_2_3_2_b"
      }
    },
    "4": {
      "0": {
        "h": "null_of_2_4_0_h",
        "b": "null_of_2_4_0_b"
      },
      "1": {
        "h": "null_of_2_4_1_h",
        "b": "null_of_2_4_1_b"
      },
      "2": {
        "h": "null_of_2_4_2_h",
        "b": "null_of_2_4_2_b"
      }
    },
    "5": {
      "0": {
        "h": "null_of_2_5_0_h",
        "b": "null_of_2_5_0_b"
      },
      "1": {
        "h": "null_of_2_5_1_h",
        "b": "null_of_2_5_1_b"
      },
      "2": {
        "h": "null_of_2_5_2_h",
        "b": "null_of_2_5_2_b"
      }
    },
    "6": {
      "0": {
        "h": "null_of_2_6_0_h",
        "b": "null_of_2_6_0_b"
      },
      "1": {
        "h": "null_of_2_6_1_h",
        "b": "null_of_2_6_1_b"
      },
      "2": {
        "h": "null_of_2_6_2_h",
        "b": "null_of_2_6_2_b"
      }
    },
    "7": {
      "0": {
        "h": "null_of_2_7_0_h",
        "b": "null_of_2_7_0_b"
      },
      "1": {
        "h": "null_of_2_7_1_h",
        "b": "null_of_2_7_1_b"
      },
      "2": {
        "h": "null_of_2_7_2_h",
        "b": "null_of_2_7_2_b"
      }
    },
    "8": {
      "0": {
        "h": "null_of_2_8_0_h",
        "b": "null_of_2_8_0_b"
      },
      "1": {
        "h": "null_of_2_8_1_h",
        "b": "null_of_2_8_1_b"
      },
      "2": {
        "h": "null_of_2_8_2_h",
        "b": "null_of_2_8_2_b"
      }
    },
    "9": {
      "0": {
        "h": "null_of_2_9_0_h",
        "b": "null_of_2_9_0_b"
      },
      "1": {
        "h": "null_of_2_9_1_h",
        "b": "null_of_2_9_1_b"
      },
      "2": {
        "h": "null_of_2_9_2_h",
        "b": "null_of_2_9_2_b"
      }
    },
    "10": {
      "0": {
        "h": "null_of_2_10_0_h",
        "b": "null_of_2_10_0_b"
      },
      "1": {
        "h": "null_of_2_10_1_h",
        "b": "null_of_2_10_1_b"
      },
      "2": {
        "h": "null_of_2_10_2_h",
        "b": "null_of_2_10_2_b"
      }
    },
    "11": {
      "0": {
        "h": "null_of_2_11_0_h",
        "b": "null_of_2_11_0_b"
      },
      "1": {
        "h": "null_of_2_11_1_h",
        "b": "null_of_2_11_1_b"
      },
      "2": {
        "h": "null_of_2_11_2_h",
        "b": "null_of_2_11_2_b"
      }
    },
    "12": {
      "0": {
        "h": "null_of_2_12_0_h",
        "b": "null_of_2_12_0_b"
      },
      "1": {
        "h": "null_of_2_12_1_h",
        "b": "null_of_2_12_1_b"
      },
      "2": {
        "h": "null_of_2_12_2_h",
        "b": "null_of_2_12_2_b"
      }
    },
    "13": {
      "0": {
        "h": "null_of_2_13_0_h",
        "b": "null_of_2_13_0_b"
      },
      "1": {
        "h": "null_of_2_13_1_h",
        "b": "null_of_2_13_1_b"
      },
      "2": {
        "h": "null_of_2_13_2_h",
        "b": "null_of_2_13_2_b"
      }
    },
    "14": {
      "0": {
        "h": "null_of_2_14_0_h",
        "b": "null_of_2_14_0_b"
      },
      "1": {
        "h": "null_of_2_14_1_h",
        "b": "null_of_2_14_1_b"
      },
      "2": {
        "h": "null_of_2_14_2_h",
        "b": "null_of_2_14_2_b"
      }
    },
    "15": {
      "0": {
        "h": "null_of_2_15_0_h",
        "b": "null_of_2_15_0_b"
      },
      "1": {
        "h": "null_of_2_15_1_h",
        "b": "null_of_2_15_1_b"
      },
      "2": {
        "h": "null_of_2_15_2_h",
        "b": "null_of_2_15_2_b"
      }
    },
    "16": {
      "0": {
        "h": "null_of_2_16_0_h",
        "b": "null_of_2_16_0_b"
      },
      "1": {
        "h": "null_of_2_16_1_h",
        "b": "null_of_2_16_1_b"
      },
      "2": {
        "h": "null_of_2_16_2_h",
        "b": "null_of_2_16_2_b"
      }
    },
    "17": {
      "0": {
        "h": "null_of_2_17_0_h",
        "b": "null_of_2_17_0_b"
      },
      "1": {
        "h": "null_of_2_17_1_h",
        "b": "null_of_2_17_1_b"
      },
      "2": {
        "h": "null_of_2_17_2_h",
        "b": "null_of_2_17_2_b"
      }
    },
    "18": {
      "0": {
        "h": "null_of_2_18_0_h",
        "b": "null_of_2_18_0_b"
      },
      "1": {
        "h": "null_of_2_18_1_h",
        "b": "null_of_2_18_1_b"
      },
      "2": {
        "h": "null_of_2_18_2_h",
        "b": "null_of_2_18_2_b"
      }
    },
    "19": {
      "0": {
        "h": "null_of_2_19_0_h",
        "b": "null_of_2_19_0_b"
      },
      "1": {
        "h": "null_of_2_19_1_h",
        "b": "null_of_2_19_1_b"
      },
      "2": {
        "h": "null_of_2_19_2_h",
        "b": "null_of_2_19_2_b"
      }
    }
  },
  "3": {
    "0": {
      "0": {
        "h": "null_of_3_0_0_h",
        "b": "null_of_3_0_0_b"
      },
      "1": {
        "h": "null_of_3_0_1_h",
        "b": "null_of_3_0_1_b"
      },
      "2": {
        "h": "null_of_3_0_2_h",
        "b": "null_of_3_0_2_b"
      }
    },
    "1": {
      "0": {
        "h": "null_of_3_1_0_h",
        "b": "null_of_3_1_0_b"
      },
      "1": {
        "h": "null_of_3_1_1_h",
        "b": "null_of_3_1_1_b"
      },
      "2": {
        "h": "null_of_3_1_2_h",
        "b": "null_of_3_1_2_b"
      }
    },
    "2": {
      "0": {
        "h": "null_of_3_2_0_h",
        "b": "null_of_3_2_0_b"
      },
      "1": {
        "h": "null_of_3_2_1_h",
        "b": "null_of_3_2_1_b"
      },
      "2": {
        "h": "null_of_3_2_2_h",
        "b": "null_of_3_2_2_b"
      }
    },
    "3": {
      "0": {
        "h": "null_of_3_3_0_h",
        "b": "null_of_3_3_0_b"
      },
      "1": {
        "h": "null_of_3_3_1_h",
        "b": "null_of_3_3_1_b"
      },
      "2": {
        "h": "null_of_3_3_2_h",
        "b": "null_of_3_3_2_b"
      }
    },
    "4": {
      "0": {
        "h": "null_of_3_4_0_h",
        "b": "null_of_3_4_0_b"
      },
      "1": {
        "h": "null_of_3_4_1_h",
        "b": "null_of_3_4_1_b"
      },
      "2": {
        "h": "null_of_3_4_2_h",
        "b": "null_of_3_4_2_b"
      }
    },
    "5": {
      "0": {
        "h": "null_of_3_5_0_h",
        "b": "null_of_3_5_0_b"
      },
      "1": {
        "h": "null_of_3_5_1_h",
        "b": "null_of_3_5_1_b"
      },
      "2": {
        "h": "null_of_3_5_2_h",
        "b": "null_of_3_5_2_b"
      }
    },
    "6": {
      "0": {
        "h": "null_of_3_6_0_h",
        "b": "null_of_3_6_0_b"
      },
      "1": {
        "h": "null_of_3_6_1_h",
        "b": "null_of_3_6_1_b"
      },
      "2": {
        "h": "null_of_3_6_2_h",
        "b": "null_of_3_6_2_b"
      }
    },
    "7": {
      "0": {
        "h": "null_of_3_7_0_h",
        "b": "null_of_3_7_0_b"
      },
      "1": {
        "h": "null_of_3_7_1_h",
        "b": "null_of_3_7_1_b"
      },
      "2": {
        "h": "null_of_3_7_2_h",
        "b": "null_of_3_7_2_b"
      }
    },
    "8": {
      "0": {
        "h": "null_of_3_8_0_h",
        "b": "null_of_3_8_0_b"
      },
      "1": {
        "h": "null_of_3_8_1_h",
        "b": "null_of_3_8_1_b"
      },
      "2": {
        "h": "null_of_3_8_2_h",
        "b": "null_of_3_8_2_b"
      }
    },
    "9": {
      "0": {
        "h": "null_of_3_9_0_h",
        "b": "null_of_3_9_0_b"
      },
      "1": {
        "h": "null_of_3_9_1_h",
        "b": "null_of_3_9_1_b"
      },
      "2": {
        "h": "null_of_3_9_2_h",
        "b": "null_of_3_9_2_b"
      }
    },
    "10": {
      "0": {
        "h": "null_of_3_10_0_h",
        "b": "null_of_3_10_0_b"
      },
      "1": {
        "h": "null_of_3_10_1_h",
        "b": "null_of_3_10_1_b"
      },
      "2": {
        "h": "null_of_3_10_2_h",
        "b": "null_of_3_10_2_b"
      }
    },
    "11": {
      "0": {
        "h": "null_of_3_11_0_h",
        "b": "null_of_3_11_0_b"
      },
      "1": {
        "h": "null_of_3_11_1_h",
        "b": "null_of_3_11_1_b"
      },
      "2": {
        "h": "null_of_3_11_2_h",
        "b": "null_of_3_11_2_b"
      }
    },
    "12": {
      "0": {
        "h": "null_of_3_12_0_h",
        "b": "null_of_3_12_0_b"
      },
      "1": {
        "h": "null_of_3_12_1_h",
        "b": "null_of_3_12_1_b"
      },
      "2": {
        "h": "null_of_3_12_2_h",
        "b": "null_of_3_12_2_b"
      }
    },
    "13": {
      "0": {
        "h": "null_of_3_13_0_h",
        "b": "null_of_3_13_0_b"
      },
      "1": {
        "h": "null_of_3_13_1_h",
        "b": "null_of_3_13_1_b"
      },
      "2": {
        "h": "null_of_3_13_2_h",
        "b": "null_of_3_13_2_b"
      }
    },
    "14": {
      "0": {
        "h": "null_of_3_14_0_h",
        "b": "null_of_3_14_0_b"
      },
      "1": {
        "h": "null_of_3_14_1_h",
        "b": "null_of_3_14_1_b"
      },
      "2": {
        "h": "null_of_3_14_2_h",
        "b": "null_of_3_14_2_b"
      }
    },
    "15": {
      "0": {
        "h": "null_of_3_15_0_h",
        "b": "null_of_3_15_0_b"
      },
      "1": {
        "h": "null_of_3_15_1_h",
        "b": "null_of_3_15_1_b"
      },
      "2": {
        "h": "null_of_3_15_2_h",
        "b": "null_of_3_15_2_b"
      }
    },
    "16": {
      "0": {
        "h": "null_of_3_16_0_h",
        "b": "null_of_3_16_0_b"
      },
      "1": {
        "h": "null_of_3_16_1_h",
        "b": "null_of_3_16_1_b"
      },
      "2": {
        "h": "null_of_3_16_2_h",
        "b": "null_of_3_16_2_b"
      }
    },
    "17": {
      "0": {
        "h": "null_of_3_17_0_h",
        "b": "null_of_3_17_0_b"
      },
      "1": {
        "h": "null_of_3_17_1_h",
        "b": "null_of_3_17_1_b"
      },
      "2": {
        "h": "null_of_3_17_2_h",
        "b": "null_of_3_17_2_b"
      }
    },
    "18": {
      "0": {
        "h": "null_of_3_18_0_h",
        "b": "null_of_3_18_0_b"
      },
      "1": {
        "h": "null_of_3_18_1_h",
        "b": "null_of_3_18_1_b"
      },
      "2": {
        "h": "null_of_3_18_2_h",
        "b": "null_of_3_18_2_b"
      }
    },
    "19": {
      "0": {
        "h": "null_of_3_19_0_h",
        "b": "null_of_3_19_0_b"
      },
      "1": {
        "h": "null_of_3_19_1_h",
        "b": "null_of_3_19_1_b"
      },
      "2": {
        "h": "null_of_3_19_2_h",
        "b": "null_of_3_19_2_b"
      }
    }
  }
}
